dockerich/__init__.py
dockerich/__main__.py
dockerich-0.0.8.dist-info/METADATA
dockerich-0.0.8.dist-info/WHEEL
dockerich-0.0.8.dist-info/entry_points.txt
dockerich-0.0.8.dist-info/top_level.txt
dockerich-0.0.8.dist-info/RECORD
